easy_jar_reader/__init__.py
easy_jar_reader/__main__.py
easy_jar_reader/config.py
easy_jar_reader/decompiler.py
easy_jar_reader/response_manager.py
easy_jar_reader/server.py
easy_jar_reader/decompilers/fernflower.jar
easy_jar_reader-0.1.3.dist-info/licenses/LICENSE
easy_jar_reader-0.1.3.dist-info/METADATA
easy_jar_reader-0.1.3.dist-info/WHEEL
easy_jar_reader-0.1.3.dist-info/entry_points.txt
easy_jar_reader-0.1.3.dist-info/top_level.txt
easy_jar_reader-0.1.3.dist-info/RECORD
