Metadata-Version: 2.4
Name: easy-jar-reader
Version: 0.1.3
Summary: MCP Server for reading Java source code from Maven JAR files with decompilation support
Author-email: FangYuan33 <fangyuan33@example.com>
Maintainer-email: FangYuan33 <fangyuan33@example.com>
License: MIT
Project-URL: Homepage, https://github.com/FangYuan33/easy-jar-reader
Project-URL: Documentation, https://github.com/FangYuan33/easy-jar-reader#readme
Project-URL: Repository, https://github.com/FangYuan33/easy-jar-reader.git
Project-URL: Issues, https://github.com/FangYuan33/easy-jar-reader/issues
Project-URL: Changelog, https://github.com/FangYuan33/easy-jar-reader/releases
Keywords: mcp,model-context-protocol,maven,jar,java,decompiler,source-code,fernflower,claude,ai-tools
Classifier: Development Status :: 4 - Beta
Classifier: Intended Audience :: Developers
Classifier: License :: OSI Approved :: MIT License
Classifier: Programming Language :: Python :: 3
Classifier: Programming Language :: Python :: 3.10
Classifier: Programming Language :: Python :: 3.11
Classifier: Programming Language :: Python :: 3.12
Classifier: Programming Language :: Java
Classifier: Topic :: Software Development :: Libraries :: Python Modules
Classifier: Topic :: Software Development :: Build Tools
Classifier: Topic :: Utilities
Requires-Python: >=3.10
License-File: LICENSE
Requires-Dist: mcp>=0.9.0
Provides-Extra: dev
Requires-Dist: pytest>=7.0.0; extra == "dev"
Requires-Dist: pytest-asyncio>=0.21.0; extra == "dev"
Requires-Dist: build>=1.0.0; extra == "dev"
Requires-Dist: twine>=4.0.0; extra == "dev"
Dynamic: license-file
